stix2extensions/__init__.py
stix2extensions/automodel/__init__.py
stix2extensions/automodel/automodel.py
stix2extensions/automodel/constants.py
stix2extensions/automodel/definitions.py
stix2extensions/automodel/extension_handlers.py
stix2extensions/automodel/property_converters.py
stix2extensions/automodel/property_extension.py
stix2extensions/definitions/__init__.py
stix2extensions/definitions/properties/__init__.py
stix2extensions/definitions/properties/identity_opencti.py
stix2extensions/definitions/properties/indicator_sigma_rule.py
stix2extensions/definitions/properties/indicators_vulnerable_cpe.py
stix2extensions/definitions/properties/location_opencti.py
stix2extensions/definitions/properties/report_epss_scoring.py
stix2extensions/definitions/properties/software_cpe_properties.py
stix2extensions/definitions/properties/vulnerability_opencti.py
stix2extensions/definitions/properties/vulnerability_scoring.py
stix2extensions/definitions/scos/__init__.py
stix2extensions/definitions/scos/ai_prompt.py
stix2extensions/definitions/scos/attack_action.py
stix2extensions/definitions/scos/bank_account.py
stix2extensions/definitions/scos/cryptocurrency_transaction.py
stix2extensions/definitions/scos/cryptocurrency_wallet.py
stix2extensions/definitions/scos/data_source.py
stix2extensions/definitions/scos/payment_card.py
stix2extensions/definitions/scos/phone_number.py
stix2extensions/definitions/scos/user_agent.py
stix2extensions/definitions/sdos/__init__.py
stix2extensions/definitions/sdos/exploit.py
stix2extensions/definitions/sdos/weakness.py
stix2extensions/examples/generate.py
stix2extensions/examples/properties/identity-opencti.py
stix2extensions/examples/properties/indicator-sigma-rule.py
stix2extensions/examples/properties/indicator-vulnerable-cpes.py
stix2extensions/examples/properties/location-opencti.py
stix2extensions/examples/properties/report-epss-scoring.py
stix2extensions/examples/properties/software-cpe-properties.py
stix2extensions-2.1.3.dist-info/METADATA
stix2extensions-2.1.3.dist-info/WHEEL
stix2extensions-2.1.3.dist-info/licenses/LICENSE
stix2extensions-2.1.3.dist-info/RECORD
