Metadata-Version: 2.4
Name: stix2extensions
Version: 2.1.3
Summary: A package containing the STIX 2.1 definitions for custom objects generated by the dogesec Community
Project-URL: Homepage, https://github.com/muchdogesec/stix2extensions
Project-URL: Issues, https://github.com/muchdogesec/stix2extensions/issues
Author: dogesec
Maintainer: dogesec
License-File: LICENSE
Classifier: License :: OSI Approved :: Apache Software License
Classifier: Operating System :: OS Independent
Classifier: Programming Language :: Python :: 3
Requires-Python: >=3.8
Requires-Dist: pydantic
Requires-Dist: requests
Requires-Dist: stix2
